Metadata-Version: 2.1
Name: vbpip
Version: 0.0.1
Summary: 基于pypi，类比pip，实现简单的vb包管理功能。
Author: PyDa5
Author-email: 1174446068@qq.com
License: MIT
